tf_crf_layer/__init__.py
tf_crf_layer/crf.py
tf_crf_layer/crf_dynamic_constraint_helper.py
tf_crf_layer/crf_helper.py
tf_crf_layer/crf_static_constraint_helper.py
tf_crf_layer/exceptions.py
tf_crf_layer/keras_utils.py
tf_crf_layer/layer.py
tf_crf_layer/numpy_crf.py
tf_crf_layer/loss/__init__.py
tf_crf_layer/loss/crf_loss.py
tf_crf_layer/metrics/__init__.py
tf_crf_layer/metrics/crf_accuracy.py
tf_crf_layer/metrics/sequence_correctness.py
tf_crf_layer/metrics/sequence_span_accuracy.py
tf_crf_layer-0.2.5.dist-info/METADATA
tf_crf_layer-0.2.5.dist-info/WHEEL
tf_crf_layer-0.2.5.dist-info/top_level.txt
tf_crf_layer-0.2.5.dist-info/RECORD
