Metadata-Version: 2.1
Name: tf-crf-layer
Version: 0.2.5
Summary: CRF layer for TensorFlow 1.x
Home-page: https://github.com/howl-anderson/tf_crf_layer
Author: Xiaoquan Kong
Author-email: u1mail2me@gmail.com
License: MIT
Platform: UNKNOWN
Requires-Dist: tensorflow
Requires-Dist: tokenizer-tools
